CHANGELOG.txt
MANIFEST.in
README.txt
setup.py
vbspython/__init__.py
vbspython/copied.txt
vbspython/tts.py
vbspython/var.txt
vbspython/variable.py
vbspython.egg-info/PKG-INFO
vbspython.egg-info/SOURCES.txt
vbspython.egg-info/dependency_links.txt
vbspython.egg-info/top_level.txt
vbspython/files/temp.txt