Metadata-Version: 2.1
Name: vbspython
Version: 0.2.1
Summary: Interact with vbscript in python.
Home-page: UNKNOWN
Author: J3ldo
Author-email: jeldojelle@gmail.com
License: MIT
Keywords: vbs vbscript vbspython
Platform: UNKNOWN
Classifier: Development Status :: 5 - Production/Stable
Classifier: Intended Audience :: Education
Classifier: Operating System :: Microsoft :: Windows :: Windows 10
Classifier: License :: OSI Approved :: MIT License
Classifier: Programming Language :: Python :: 3
Classifier: Programming Language :: Python :: 3.7
Classifier: Programming Language :: Python :: 3.9
